hyperpod_cluster_stack_template/__init__.py
hyperpod_cluster_stack_template/creation_template.yaml
hyperpod_cluster_stack_template/registry.py
hyperpod_cluster_stack_template/v1_0/__init__.py
hyperpod_cluster_stack_template/v1_0/model.py
hyperpod_cluster_stack_template/v1_0/schema.json
hyperpod_cluster_stack_template/v1_0/template.py
hyperpod_cluster_stack_template-1.0.1.dist-info/METADATA
hyperpod_cluster_stack_template-1.0.1.dist-info/WHEEL
hyperpod_cluster_stack_template-1.0.1.dist-info/top_level.txt
hyperpod_cluster_stack_template-1.0.1.dist-info/RECORD
