Metadata-Version: 2.4
Name: hyperpod-cluster-stack-template
Version: 1.0.1
Summary: Versioned JSON-schema + Pydantic models for HyperpodPytorchJobOperator
Author: Amazon Web Services
License: Apache-2.0
Requires-Python: >=3.8
Requires-Dist: pydantic
